django_messages/__init__.py
django_messages/admin.py
django_messages/apps.py
django_messages/models.py
django_messages/tests.py
django_messages/views.py
django_messages/migrations/0001_initial.py
django_messages/migrations/0002_auto_20201028_1643.py
django_messages/migrations/__init__.py
django_basic_messages-1.0.3.dist-info/LICENSE
django_basic_messages-1.0.3.dist-info/METADATA
django_basic_messages-1.0.3.dist-info/WHEEL
django_basic_messages-1.0.3.dist-info/top_level.txt
django_basic_messages-1.0.3.dist-info/RECORD
