Metadata-Version: 2.1
Name: django-basic-messages
Version: 1.0.3
Summary: A simple re-usable Django application for sending and receiving messages from within django.
Home-page: https://github.com/jonathanmorgan/django_messages
Author: Jonathan Morgan
Author-email: jonathan.morgan.007@gmail.com
License: UNKNOWN
Platform: UNKNOWN
Classifier: Programming Language :: Python :: 3
Classifier: License :: OSI Approved :: GNU Lesser General Public License v3 or later (LGPLv3+)
Classifier: Operating System :: OS Independent
Classifier: Development Status :: 5 - Production/Stable
Classifier: Framework :: Django
Classifier: Intended Audience :: Developers
Classifier: Intended Audience :: Science/Research
Classifier: Topic :: Utilities
Requires-Python: >=3.6
Requires-Dist: django
Requires-Dist: django-taggit
Requires-Dist: python-utilities-jsm
Requires-Dist: django-basic-config
